bullscatch_backtest/__init__.py
bullscatch_backtest/config.py
bullscatch_backtest/expiry_list_spa.py
bullscatch_backtest/multidate_option_chain_spa.py
bullscatch_backtest/option_chain_spa.py
bullscatch_backtest/spot_fetch_spa.py
bullscatch-0.2.2.dist-info/METADATA
bullscatch-0.2.2.dist-info/WHEEL
bullscatch-0.2.2.dist-info/top_level.txt
bullscatch-0.2.2.dist-info/RECORD
