Metadata-Version: 2.1
Name: bullscatch
Version: 0.2.2
Summary: A package for backtesting trading strategies meant for Bullscatch Securities
Author: Bullscatch Securities
Author-email: info@bullscatchsecurities.com
Classifier: Programming Language :: Python :: 3
Classifier: License :: OSI Approved :: MIT License
Classifier: Operating System :: OS Independent
Requires-Python: >=3.6
Requires-Dist: pandas
Requires-Dist: psycopg2
